News_NLP/GNews.py
News_NLP/__init__.py
News_NLP/clf_sa.py
News_NLP/geolocator.py
News_NLP/gpr_classifier.py
News_NLP/merger_row.py
News_NLP/news_unified_model_V3.pkl
News_NLP/preprocessing.py
News_NLP/sentiment_clf.py
News_NLP/topics_for_classifier_V2.csv
News_NLP/transformed_news.xlsx
news_nlp-1.0.22.dist-info/METADATA
news_nlp-1.0.22.dist-info/LICENSE.txt
news_nlp-1.0.22.dist-info/WHEEL
news_nlp-1.0.22.dist-info/RECORD
