Metadata-Version: 2.1
Name: news-nlp
Version: 1.0.22
Summary: This package aims to collect news data via Google News API, preporcessing, implement pretrained news type classifer, sentiment classifier and perform statistical hierarchy predictive model for news event and then implememnt multiple geolocator.
Author: Jason Lu
Author-email: luzhenxian@hotmail.com
Requires-Python: >=3.8,<4.0
Classifier: Programming Language :: Python :: 3
Classifier: Programming Language :: Python :: 3.8
Classifier: Programming Language :: Python :: 3.9
Classifier: Programming Language :: Python :: 3.10
Classifier: Programming Language :: Python :: 3.11
Requires-Dist: gdown (==4.6.2)
Requires-Dist: mediacloud-cliff (==2.6.1)
Requires-Dist: newsapi-python (>=0.2.6,<0.3.0)
Requires-Dist: nltk (>=3.8.1,<4.0.0)
Requires-Dist: openpyxl (==3.1.0)
Requires-Dist: scikit-learn (>=1.2.1,<2.0.0)
Requires-Dist: spacy (>=3.4.0,<4.0.0)
